README
setup.py
rdfsim/__init__.py
rdfsim/space.py
rdfsim.egg-info/PKG-INFO
rdfsim.egg-info/SOURCES.txt
rdfsim.egg-info/dependency_links.txt
rdfsim.egg-info/requires.txt
rdfsim.egg-info/top_level.txt