Metadata-Version: 1.0
Name: rdfsim
Version: 0.3
Summary: Modelling RDF data as a vector space
Home-page: UNKNOWN
Author: Yves Raimond
Author-email: yves.raimond@bbc.co.uk
License: UNKNOWN
Platform: UNKNOWN
